<pair>
<id>0</id>
<doc_id>10365689</doc_id>
<doc_id>10372602</doc_id>
<doc_id>10366234</doc_id>
</pair>
<pair>
<id>1</id>
<doc_id>13394061</doc_id>
<doc_id>13377372</doc_id>
<doc_id>10781778</doc_id>
</pair>
<pair>
<id>2</id>
<doc_id>10824477</doc_id>
<doc_id>10822682</doc_id>
<doc_id>10825393</doc_id>
</pair>
<pair>
<id>3</id>
<doc_id>11086272</doc_id>
<doc_id>10482258</doc_id>
<doc_id>10482437</doc_id>
</pair>
<pair>
<id>4</id>
<doc_id>12782702</doc_id>
<doc_id>10466159</doc_id>
<doc_id>10105996</doc_id>
</pair>
<pair>
<id>5</id>
<doc_id>12171411</doc_id>
<doc_id>12154084</doc_id>
<doc_id>12156694</doc_id>
</pair>
<pair>
<id>6</id>
<doc_id>12263137</doc_id>
<doc_id>12483331</doc_id>
<doc_id>12367599</doc_id>
</pair>
<pair>
<id>7</id>
<doc_id>13197524</doc_id>
<doc_id>13324368</doc_id>
<doc_id>13322307</doc_id>
</pair>
<pair>
<id>8</id>
<doc_id>11870621</doc_id>
<doc_id>11872175</doc_id>
<doc_id>12082485</doc_id>
</pair>
<pair>
<id>9</id>
<doc_id>11772232</doc_id>
<doc_id>11768974</doc_id>
<doc_id>11770254</doc_id>
</pair>
<pair>
<id>10</id>
<doc_id>11092876</doc_id>
<doc_id>10138558</doc_id>
<doc_id>9926682</doc_id>
</pair>
<pair>
<id>11</id>
<doc_id>11136413</doc_id>
<doc_id>10839989</doc_id>
<doc_id>10167143</doc_id>
</pair>
<pair>
<id>12</id>
<doc_id>11155739</doc_id>
<doc_id>11155970</doc_id>
<doc_id>11134760</doc_id>
</pair>
<pair>
<id>13</id>
<doc_id>13055100</doc_id>
<doc_id>13142685</doc_id>
<doc_id>13495829</doc_id>
</pair>
<pair>
<id>14</id>
<doc_id>12209942</doc_id>
<doc_id>12458844</doc_id>
<doc_id>12521721</doc_id>
</pair>
<pair>